LICENSE.txt
MANIFEST.in
README.md
setup.cfg
setup.py
django_executor/__init__.py
django_executor/admin.py
django_executor/apps.py
django_executor/base.py
django_executor/models.py
django_executor/settings.py
django_executor/urls.py
django_executor/views.py
django_executor.egg-info/PKG-INFO
django_executor.egg-info/SOURCES.txt
django_executor.egg-info/dependency_links.txt
django_executor.egg-info/not-zip-safe
django_executor.egg-info/top_level.txt
django_executor/migrations/0001_initial.py
django_executor/migrations/__init__.py
django_executor/staticfiles/css/bootstrap-theme.css
django_executor/staticfiles/css/bootstrap-theme.min.css
django_executor/staticfiles/css/bootstrap.css
django_executor/staticfiles/css/bootstrap.min.css
django_executor/staticfiles/css/management-executor.css
django_executor/staticfiles/js/bootstrap.js
django_executor/staticfiles/js/bootstrap.min.js
django_executor/staticfiles/js/cookiesetter.js
django_executor/staticfiles/js/jquery-1.12.0.min.js
django_executor/staticfiles/js/management-executor.js
django_executor/staticfiles/js/npm.js
django_executor/templates/django_executor/base.html
django_executor/templates/django_executor/manage-commands.html