Metadata-Version: 1.0
Name: django-executor
Version: 0.0.1
Summary: Manage your django management commands easily within your browser
Home-page: https://github.com/willandskill/django-executor
Author: Will & Skill
Author-email: info@willandskill.se
License: MIT licence, see LICENCE.txt
Platform: UNKNOWN
